{
    "version": 1,
    "source": {
        "path": "/src/pages/2022/ag06modification/unscrew.jpg",
        "hash": "vC5x1twvafrRbk8jBUfgkdZh-D5nimKNQL8Wfct_I04",
        "width": 1600,
        "height": 1200,
        "size": 420843
    },
    "results": [
        {
            "path": "/images/kguox-HU/w600.8QmiF8ds.webp",
            "hash": "8QmiF8ds_n3y0nf1soRsyFf3MKrsi1VwhhwZ5mD2LnQ",
            "width": 600,
            "height": 450,
            "size": 19092
        },
        {
            "path": "/images/kguox-HU/w600.QEzTS910.jpg",
            "hash": "QEzTS910U6JC7VQ8xHh1_QcULaaI8UZP64sS6IVs_SM",
            "width": 600,
            "height": 450,
            "size": 24900
        },
        {
            "path": "/images/kguox-HU/w600.vVy5MjPW.avif",
            "hash": "vVy5MjPWSTsarsbreu5WXs1ZIw06OBjx8FXo4WSk-aM",
            "width": 600,
            "height": 450,
            "size": 13102
        },
        {
            "path": "/images/kguox-HU/w800.QsW_suqD.jpg",
            "hash": "QsW_suqDL3n4hK-gzGk0s8_tsoJR_sA4I2en3lcRzaw",
            "width": 800,
            "height": 600,
            "size": 38277
        },
        {
            "path": "/images/kguox-HU/w800.jlkrqWr8.webp",
            "hash": "jlkrqWr8wzVZBZKp_7Stcs-B3mQl-zjNezX-HB1fSKA",
            "width": 800,
            "height": 600,
            "size": 27664
        },
        {
            "path": "/images/kguox-HU/w800.auUN096y.avif",
            "hash": "auUN096yBupnGtYq559M8eIJk50Q3aIQDAXb6dXtXLI",
            "width": 800,
            "height": 600,
            "size": 18156
        },
        {
            "path": "/images/kguox-HU/w1000.oFxg0fG6.jpg",
            "hash": "oFxg0fG6abK_zAVKceELo5gXmUVFkDQ8lkvtgd3Gqdk",
            "width": 1000,
            "height": 750,
            "size": 53338
        },
        {
            "path": "/images/kguox-HU/w1000.93AhnwCq.webp",
            "hash": "93AhnwCqor7SygX9IiO-wo2jfoNDLN2zyi6-wcPBC7U",
            "width": 1000,
            "height": 750,
            "size": 37668
        },
        {
            "path": "/images/kguox-HU/w1000.70JMZwYJ.avif",
            "hash": "70JMZwYJ_c_5xJ0Zvf8Ok3IHzYOp2VumXeNDFOG6dlw",
            "width": 1000,
            "height": 750,
            "size": 23870
        },
        {
            "path": "/images/kguox-HU/w1200._lmxn6BK.jpg",
            "hash": "_lmxn6BKvbWIO4NuDa9ceHlzkbYz1196XzMtDaIiYL0",
            "width": 1200,
            "height": 900,
            "size": 69743
        },
        {
            "path": "/images/kguox-HU/w1200.7vsgJp-t.webp",
            "hash": "7vsgJp-tFGTiBpRMEeOgdOqPdNMnxldUHI_In-POjKs",
            "width": 1200,
            "height": 900,
            "size": 48250
        },
        {
            "path": "/images/kguox-HU/w1200.J55i_HvK.avif",
            "hash": "J55i_HvKi6z7zgjAXYxUi5Gb5wTdf_BKJPkIhtK9Ktw",
            "width": 1200,
            "height": 900,
            "size": 29971
        },
        {
            "path": "/images/kguox-HU/w1500.zzMBweEp.jpg",
            "hash": "zzMBweEphJEsnkeebuQGlCzmzZ8Lnzd9x_bx3DNINqA",
            "width": 1500,
            "height": 1125,
            "size": 97653
        },
        {
            "path": "/images/kguox-HU/w1500.yg6wWVbR.webp",
            "hash": "yg6wWVbR5aNH-uqsZP0zr20IP2MSpOZjEIePrMP6hM8",
            "width": 1500,
            "height": 1125,
            "size": 65584
        },
        {
            "path": "/images/kguox-HU/w1500.Rpap3W5q.avif",
            "hash": "Rpap3W5qeh7SoKwD_jtto8duJThSAtXQlDRLG_c4m7w",
            "width": 1500,
            "height": 1125,
            "size": 38687
        }
    ]
}